pyaweminerapi/__init__.py
pyaweminerapi-0.5.dist-info/DESCRIPTION.rst
pyaweminerapi-0.5.dist-info/METADATA
pyaweminerapi-0.5.dist-info/RECORD
pyaweminerapi-0.5.dist-info/WHEEL
pyaweminerapi-0.5.dist-info/metadata.json
pyaweminerapi-0.5.dist-info/top_level.txt
