Metadata-Version: 2.0
Name: pyaweminerapi
Version: 0.5
Summary: Simple Python API Wrapper for AwesomeMiner
Home-page: http://github.com/concongo/pyaweminerapi
Author: J. Fernando Gonzalez
Author-email: jfgonzalem@gmail.com
License: MIT
Keywords: API Awesome Miner
Platform: UNKNOWN
Requires-Python: >=2.6,<3
